hermesConnector/__init__.py
hermesConnector/connector.py
hermesConnector/connector_alpaca.py
hermesConnector/connector_binance.py
hermesConnector/connector_template.py
hermesConnector/hermes_enums.py
hermesConnector/hermes_exceptions.py
hermesConnector/models.py
hermesConnector/models_utilities.py
hermesConnector/timeframe.py
hermesconnector-0.1.0.dist-info/licenses/LICENSE
hermesconnector-0.1.0.dist-info/METADATA
hermesconnector-0.1.0.dist-info/WHEEL
hermesconnector-0.1.0.dist-info/top_level.txt
hermesconnector-0.1.0.dist-info/RECORD
